Metadata-Version: 2.1
Name: spsearch
Version: 0.1.0
Summary: Python tools to get species data from various API.
Home-page: https://github.com/AzukiOtter/spsearch
Author: AzukiOtter
Author-email: ogran.std@gmail.com
License: GPL-3.0
Keywords: bioinformatics biology biodiversity species
Platform: UNKNOWN
Classifier: Development Status :: 3 - Alpha
Classifier: Intended Audience :: Developers
Classifier: Topic :: Scientific/Engineering :: Bio-Informatics
Classifier: Programming Language :: Python :: 3.6
Classifier: Programming Language :: Python :: 3.7
Requires-Python: >=3.6, <4
